mpltable/__init__.py
mpltable/options.py
mpltable/table.py
matplotlib_table-0.0.3.dist-info/LICENSE
matplotlib_table-0.0.3.dist-info/METADATA
matplotlib_table-0.0.3.dist-info/WHEEL
matplotlib_table-0.0.3.dist-info/top_level.txt
matplotlib_table-0.0.3.dist-info/RECORD
